{
  "hooks": {
    "postToolUse": [
      {
        "type": "command",
        "bash": "command -v lean-ctx >/dev/null 2>&1 || exit 0; lean-ctx hook observe",
        "timeoutSec": 5
      }
    ],
    "preToolUse": [
      {
        "type": "command",
        "bash": "command -v lean-ctx >/dev/null 2>&1 || exit 0; lean-ctx hook rewrite",
        "timeoutSec": 15
      },
      {
        "type": "command",
        "bash": "command -v lean-ctx >/dev/null 2>&1 || exit 0; lean-ctx hook redirect",
        "timeoutSec": 5
      }
    ]
  },
  "version": 1
}
